jsontree.py
jsontree-0.5.0.dist-info/LICENSE.txt
jsontree-0.5.0.dist-info/METADATA
jsontree-0.5.0.dist-info/WHEEL
jsontree-0.5.0.dist-info/top_level.txt
jsontree-0.5.0.dist-info/RECORD
